LICENSE
serato_crate/__init__.py
serato_crate/crate_file.py
serato_crate/py.typed
serato_crate/serato_crate.py
serato_crate-0.0.1.dist-info/LICENSE
serato_crate-0.0.1.dist-info/METADATA
serato_crate-0.0.1.dist-info/WHEEL
serato_crate-0.0.1.dist-info/RECORD
